.DS_Store
CYDataAccess/CYDataAccess.py
CYDataAccess/__init__.py
CYDataAccess/cli.py
cy_data_access/__init__.py
cy_data_access/cli.py
cy_data_access/cy_data_access.py
cy_data_access/user_cli.py
cy_data_access/connection/__init__.py
cy_data_access/connection/connect.py
cy_data_access/connection/influxdb.py
cy_data_access/connection/mysql.py
cy_data_access/models/__init__.py
cy_data_access/models/backtest.py
cy_data_access/models/config.py
cy_data_access/models/crawler.py
cy_data_access/models/financial.py
cy_data_access/models/log.py
cy_data_access/models/market.py
cy_data_access/models/position.py
cy_data_access/models/quant.py
cy_data_access/models/user.py
cy_data_access/util/__init__.py
cy_data_access/util/convert.py
cy_data_access-0.4.25.dist-info/LICENSE
cy_data_access-0.4.25.dist-info/METADATA
cy_data_access-0.4.25.dist-info/WHEEL
cy_data_access-0.4.25.dist-info/entry_points.txt
cy_data_access-0.4.25.dist-info/top_level.txt
cy_data_access-0.4.25.dist-info/RECORD
