Metadata-Version: 2.1
Name: cy-data-access
Version: 0.4.25
Summary: DataAccess of quant app
Home-page: https://github.com/cragod/CYDataAccess
Author: CY Gatro
Author-email: cragodn@gmail.com
License: MIT license
Keywords: cy_data_access
Platform: UNKNOWN
Classifier: Development Status :: 2 - Pre-Alpha
Classifier: Intended Audience :: Developers
Classifier: License :: OSI Approved :: MIT License
Classifier: Natural Language :: English
Classifier: Programming Language :: Python :: 3
Classifier: Programming Language :: Python :: 3.5
Classifier: Programming Language :: Python :: 3.6
Classifier: Programming Language :: Python :: 3.7
Classifier: Programming Language :: Python :: 3.8
Requires-Python: >=3.5
Requires-Dist: Click (>=7.0)
Requires-Dist: pymodm (>=0.4.2)
Requires-Dist: influxdb-client (>=1.14.0)
Requires-Dist: pymysql (>=0.9.3)
Requires-Dist: sqlalchemy (>=1.3.15)
